LICENSE.txt
README.md
setup.cfg
setup.py
KnowledgeBase/model.py
KnowledgeBase.egg-info/PKG-INFO
KnowledgeBase.egg-info/SOURCES.txt
KnowledgeBase.egg-info/dependency_links.txt
KnowledgeBase.egg-info/requires.txt
KnowledgeBase.egg-info/top_level.txt
bin/knowledge.py
bin/outline.py