Metadata-Version: 2.1
Name: KnowledgeBase
Version: 1.3
Home-page: https://github.com/eddo888/KnowledgeBase
Download-URL: https://github.com/eddo888/KnowledgeBase/archive/1.3.tar.gz
Author: David Edson
Author-email: eddo888@tpg.com.au
License: MIT
License-File: LICENSE.txt
